logNow/__init__.py
logNow/functions.py
logNow/logNow.py
logNow/logNow_exampel.py
logNow-0.2.2.dist-info/LICENSE
logNow-0.2.2.dist-info/METADATA
logNow-0.2.2.dist-info/WHEEL
logNow-0.2.2.dist-info/top_level.txt
logNow-0.2.2.dist-info/RECORD
